aiogbchat-0.4.dist-info/DESCRIPTION.rst
aiogbchat-0.4.dist-info/METADATA
aiogbchat-0.4.dist-info/RECORD
aiogbchat-0.4.dist-info/WHEEL
aiogbchat-0.4.dist-info/entry_points.txt
aiogbchat-0.4.dist-info/metadata.json
aiogbchat-0.4.dist-info/top_level.txt
aiogbclient/__init__.py
aiogbclient/__main__.py
aiogbclient/client_config.py
aiogbclient/main.py
aiogbclient/run.py
aiogbclient/database/__init__.py
aiogbclient/database/controller.py
aiogbclient/database/db_connector.py
aiogbclient/database/models.py
aiogbclient/ui/__init__.py
aiogbclient/ui/chat_ui.py
aiogbclient/ui/contacts_ui.py
aiogbclient/ui/login_ui.py
aiogbclient/ui/windows.py
aiogbclient/utils/__init__.py
aiogbclient/utils/client_messages.py
aiogbclient/utils/client_proto.py
aiogbclient/utils/log_config.py
aiogbclient/utils/mixins.py
aiogbserver/__init__.py
aiogbserver/__main__.py
aiogbserver/main.py
aiogbserver/run.py
aiogbserver/server_config.py
aiogbserver/database/__init__.py
aiogbserver/database/controller.py
aiogbserver/database/db_connector.py
aiogbserver/database/models.py
aiogbserver/ui/__init__.py
aiogbserver/ui/server_monitor_ui.py
aiogbserver/ui/windows.py
aiogbserver/utils/__init__.py
aiogbserver/utils/log_config.py
aiogbserver/utils/mixins.py
aiogbserver/utils/server_messages.py
aiogbserver/utils/server_proto.py
