Metadata-Version: 2.0
Name: aiogbchat
Version: 0.4
Summary: Async Client-Server
Home-page: https://github.com/achicha/chat/
Author: achicha
Author-email: UNKNOWN
License: GNU General Public License v3.0
Keywords: client,server,asyncio,Qt
Platform: UNKNOWN
Requires-Dist: PyQt5
Requires-Dist: quamash
Requires-Dist: sqlalchemy
